_pytorch_fast_elmo
pytorch_fast_elmo
